LICENSE
README
setup.py
asyncamqp/__init__.py
asyncamqp/channel.py
asyncamqp/compat.py
asyncamqp/consumer.py
asyncamqp/exceptions.py
asyncamqp.egg-info/PKG-INFO
asyncamqp.egg-info/SOURCES.txt
asyncamqp.egg-info/dependency_links.txt
asyncamqp.egg-info/requires.txt
asyncamqp.egg-info/top_level.txt