Metadata-Version: 2.1
Name: asyncamqp
Version: 0.1.7
Summary: aioampq without callbacks!
Home-page: https://github.com/jucacrispim/asyncamqp
Author: Juca Crispim
Author-email: juca@poraodojuca.net
License: GPL
Provides: asyncamqp
License-File: LICENSE
